[
  {
    "schemaVersion": 1,
    "recordedAt": "2026-06-02T12:58:25.269756+00:00",
    "gitSha": "06b102660885e5129a787a8fbe30ab141a2c200d",
    "metrics": {}
  },
  {
    "schemaVersion": 1,
    "recordedAt": "2026-06-02T13:20:08.840183+00:00",
    "gitSha": "de718a8ea0d592f899177de1a5ef4944e293e734",
    "metrics": {}
  },
  {
    "schemaVersion": 1,
    "recordedAt": "2026-06-02T13:51:16.473459+00:00",
    "gitSha": "d8b30a1be16c0573406fd1ec5f37c69555a4248c",
    "metrics": {}
  },
  {
    "schemaVersion": 1,
    "recordedAt": "2026-06-03T07:55:08.197447+00:00",
    "gitSha": "15fa07c59d856d1532575e6a62718dbd30587217",
    "metrics": {}
  }
]